{
  "metadata": {},
  "startPage": "/anghenion-cyllid",
  "backLinkText": "Dychwelyd i arolwg y cais",
  "pages": [
    {
      "title": "Anghenion cyllid",
      "path": "/anghenion-cyllid",
      "components": [
        {
          "name": "RgwAoN",
          "options": {},
          "type": "Para",
          "content": "<label class=\"govuk-!-font-weight-bold\">Yn yr adran hon, byddwn yn gofyn am:\n</label>\n\n<ul class=\"govuk-list govuk-list--bullet\">\n<li>eich cais am gyllid cyfalaf</li>\n<li>cyllid cydweddu rydych wedi ei nodi neu ei sicrhau</li>\n<li>eich cais am gyllid refeniw (dewisol)</li>\n<li>disgrifiad o'ch costau refeniw</li>\n</ul>"
        }
      ],
      "next": [
        {
          "path": "/cais-am-gyllid-cyfalaf"
        }
      ],
      "controller": "./pages/start.js"
    },
    {
      "path": "/cais-am-gyllid-cyfalaf",
      "title": "Cais am gyllid cyfalaf",
      "components": [
        {
          "name": "ngpQfE",
          "options": {},
          "type": "Details",
          "title": "Cymorth gyda'r achos rheoli",
          "content": "Rydym yn bwriadu deall:\n<div>\n<br>\n<ul class=\"govuk-list govuk-list--bullet\">\n<li>faint o gyllid rydych yn ei wneud cais amdano o'r gronfa hon</li>\n<li>eich costau gweithredol cyflawn</li>\n<li>unrhyw gyllid rydych eisoes wedi ei dderbyn ar gyfer eich prosiect hyd yma</li>\n<li>unrhyw gyllid rydych yn bwriadu'i sicrhau ar gyfer eich prosiect</li>\n<li>unrhyw gyllid rydych eisoes wedi ei dderbyn tuag at gostau cyfalaf</li>\n</ul>\n<p>Byddwn yn gofyn i chi uwchlwytho cynllun busnes i gefnogi'r atebion rydych yn eu rhoi i ni yn yr adran hon.</p>\n</div>"
        },
        {
          "name": "iPBHAo",
          "options": {},
          "type": "Html",
          "content": "<p class=\"govuk-caption-m\">Costau cyfalaf yw costau prynu neu lesu'ch ased a thalu am gostyngiad.</p>\n\n<p class=\"govuk-caption-m\">Bydd Cronfa Perchnogaeth Gymunedol (COF) yn cyllido hyd at 80% o gostau cyfalaf cyflawn eich prosiect, hyd at uchafswm o £2 filiwn.</p>\n\n<p class=\"govuk-caption-m\">Rhaid talu am o leiaf 20% o gostau cyfalaf cyflawn eich prosiect drwy ffynonellau eraill (cyllid cydweddu). Er enghraifft:</p>\n\n<ul class=\"govuk-list govuk-list--bullet\">\n<li>Rydych eisiau prynu ased cymunedol sy'n costio £2,500,000. Gallwch wneud cais am £2m o COF, a rhaid codi'r £500,000 sy'n weddill o ffynonellau eraill.</li>\n<li>Rydych eisiau prynu ased cymunedol sy'n costio £250,000. Gallwch wneud cais am £200,000 o COF, a rhaid codi'r £50,000 sy'n weddill o ffynonellau eraill.</li>\n</ul>\n\n<p class=\"govuk-caption-m\">(Mewn amgylchiadau eithriadol, efallai y bydd angen i chi sicrhau dim ond 10% mewn cyllid cydweddu. Bydd eich darparwr cymorth datblygu eisoes wedi cadarnhau hyn gyda chi os ydych yn gymwys.)</p>\n\n<p class=\"govuk-caption-m\">Os llwyddiannus, rhaid i chi wario'r holl gyllid o fewn 12 mis.</p>"
        },
        {
          "name": "ABROnB",
          "options": {
            "prefix": "£",
            "classes": "govuk-!-width-one-third",
            "hideTitle": false
          },
          "type": "NumberField",
          "title": "",
          "hint": "<label class=\"govuk-body\" for=\"ABROnB\">Cais am gyllid cyfalaf</label>"
        },
        {
          "name": "hJkmBS",
          "options": {},
          "type": "YesNoField",
          "title": "Os llwyddiannus, a wnewch chi ddefnyddio'ch cyllid o fewn y 12 mis nesaf?"
        }
      ],
      "next": [
        {
          "path": "/costau-cyfalaf-ar-gyfer-eich-prosiect"
        }
      ],
      "section": "bgUGuD"
    },
    {
      "path": "/eich-atebion-llenwir",
      "title": "Gwiriwch eich atebion",
      "controller": "./pages/summary.js",
      "components": [],
      "next": [],
      "section": "bgUGuD"
    },
    {
      "path": "/costau-cyfalaf-ar-gyfer-eich-prosiect",
      "title": "Costau cyfalaf ar gyfer eich prosiect",
      "controller": "RepeatingFieldPageController",
      "options": {
        "summaryDisplayMode": {
          "samePage": true,
          "separatePage": false,
          "hideRowTitles": false
        },
        "customText": {
          "samePageTitle": "Eich costau cyfalaf"
        }
      },
      "components": [
        {
          "name": "GaAAPb",
          "options": {},
          "type": "Details",
          "content": "Rydym yn bwriadu deall:\n<div>\n<br>\n<ul class=\"govuk-list govuk-list--bullet\">\n<li>faint o gyllid rydych yn ei wneud cais amdano o'r gronfa hon</li>\n<li>eich costau gweithredol cyflawn </li>\n<li>unrhyw gyllid rydych eisoes wedi ei dderbyn ar gyfer eich prosiect hyd yma</li>\n<li>unrhyw gyllid rydych yn bwriadu'i sicrhau ar gyfer eich prosiect</li>\n<li>unrhyw gyllid rydych eisoes wedi ei dderbyn tuag at gostau cyfalaf</li>\n</ul>\n<p>Byddwn yn gofyn i chi uwchlwytho cynllun busnes i gefnogi'r atebion rydych yn eu rhoi i ni yn yr adran hon.</p>\n</div>",
          "title": "Cymorth gyda'r achos rheoli"
        },
        {
          "name": "EaxCoo",
          "options": {},
          "type": "Para",
          "content": "<h2 class=\"govuk-heading-s\">Costau cyfalaf</h2>\n\n<p class=\"govuk-hint\">Dywedwch wrthym am gostau cyfalaf cyflawn eich prosiect.</p>\n\n<p class=\"govuk-hint\">Dylai hyn fod ar gyfer y prosiect cyfan, nid yn unig yr hyn rydych yn gofyn amdano o'r gronfa.</p>\n\n<p class=\"govuk-hint\">Gellir defnyddio costau cyfalaf i:</p>\n<ul class=\"govuk-list govuk-list--bullet\">\n<li>prynu neu lesu'r aset</li>\n<li>talu am gostyngiad</li>\n</ul>\n</p>\n<p class=\"govuk-hint\">Cofiwch, gallwch wneud cais am hyd at 80% (neu 90% os yw'r darparwr cymorth datblygu wedi cadarnhau eich bod yn gymwys i wneud hyn) o'ch costau cyfalaf, hyd at uchafswm o £2 filiwn.</p>\n<p class=\"govuk-hint\">Gallwch ddefnyddio'ch cynllun busnes i roi gwybodaeth sy'n cefnogi'ch atebion.</p>\n\n\n\n"
        },
        {
          "name": "qQLyXL",
          "options": {
            "prefix": "£",
            "columnTitles": ["Disgrifiad", "Swm", "Gweithred"],
            "required": true
          },
          "type": "MultiInputField",
          "title": "Costau cyfalaf",
          "hint": "Y MultiInputField sydd ei angen",
          "schema": {},
          "children": [
            {
              "name": "GLQlOh",
              "options": {},
              "type": "TextField",
              "title": "Disgrifiwch y gost"
            },
            {
              "name": "JtwkMy",
              "options": {
                "prefix": "£",
                "classes": "govuk-!-width-one-half"
              },
              "type": "NumberField",
              "title": "Swm",
              "hint": "",
              "schema": {}
            }
          ]
        }
      ],
      "next": [
        {
          "path": "/os-ydych-chi-wedie-sicrhau-cyllid-cyfatebol"
        }
      ],
      "section": "bgUGuD"
    },
    {
      "path": "/os-ydych-chi-wedie-sicrhau-cyllid-cyfatebol",
      "title": "Os ydych chi wedi sicrhau cyllid cyfatebol",
      "components": [
        {
          "name": "LVKBMP",
          "options": {},
          "type": "Para",
          "content": "<p class=\"govuk-hint\">Rhaid i o leiaf 20% o eich costau cyfalaf cyfanswm gael eu talu gan eich sefydliad neu arianwr arall (cyllid cyfatebol).</p>\n\n<p class=\"govuk-hint\">Gall ffynonellau cyllid cyfatebol gynnwys:\n<ul class=\"govuk-hint\">\n<li>cyrff cyhoeddus</li>\n<li>gweinyddiaethau datganoledig</li>\n<li>ymddiriedolaethau elusennol</li>\n<li>cyllid y loteri genedlaethol</li>\n<li>cyfranddaliadau cymunedol</li>\n<li>buddsoddwyr cymdeithasol</li>\n<li>benthycwyr eraill</li>\n</ul>\n</p>\n<p class=\"govuk-hint\">Nid oes angen i chi wedi sicrhau holl eich cyllid cyfatebol eto, ond dylech fod wedi nodi arianwyr posibl.</p>\n\n"
        },
        {
          "name": "DOvZvB",
          "options": {},
          "type": "YesNoField",
          "title": "A ydych chi wedi sicrhau unrhyw gyllid cyfatebol eto?"
        }
      ],
      "next": [
        {
          "path": "/cyllid-cyfatebol-sicrhiedig",
          "condition": "QyNLbn"
        },
        {
          "path": "/cyllid-cyfatebol-dihysbys",
          "condition": "nzrkpu"
        }
      ],
      "section": "bgUGuD"
    },
    {
      "path": "/cyllid-cyfatebol-sicrhiedig",
      "title": "Cyllid cyfatebol sicrhiedig",
      "controller": "RepeatingFieldPageController",
      "options": {
        "summaryDisplayMode": {
          "samePage": true,
          "separatePage": false,
          "hideRowTitles": false
        },
        "customText": {
          "samePageTitle": "Eich cyllid cyfatebol sicrhiedig"
        }
      },
      "components": [
        {
          "name": "LZUkqw",
          "options": {},
          "type": "Para",
          "content": "<h2 class=\"govuk-heading-s\">Cyllid cyfatebol sicrhiedig</h2>\n\n<p class=\"govuk-hint\">Dywedwch wrthym pa ffynonellau cyllid rydych eisoes wedi eu sicrhau fel cyllid cyfatebol.</p>\n\n<p class=\"govuk-hint\">Gall ffynonellau cyllid cyfatebol gynnwys:\n<ul class=\"govuk-hint\">\n<li>cyrff cyhoeddus</li>\n<li>gweinyddiaethau datganoledig</li>\n<li>ymddiriedolaethau elusennol</li>\n<li>cyllid y loteri genedlaethol</li>\n<li>cyfranddaliadau cymunedol</li>\n<li>buddsoddwyr cymdeithasol</li>\n<li>benthycwyr eraill</li>\n</ul>\n</p>"
        },
        {
          "name": "MopCmv",
          "options": {
            "prefix": "£",
            "columnTitles": ["Ffynnonell", "Swm", "Gweithred"],
            "required": true
          },
          "type": "MultiInputField",
          "title": "Cyllid cyfatebol sicrhiedig",
          "hint": "Y MultiInputField sydd ei angen",
          "schema": {},
          "children": [
            {
              "name": "JKqLWU",
              "options": {},
              "type": "TextField",
              "title": "Ffynnonell o gyllid sicrhiedig"
            },
            {
              "name": "LVJcDC",
              "options": {
                "prefix": "£",
                "classes": "govuk-!-width-one-half"
              },
              "type": "NumberField",
              "title": "Swm",
              "hint": "",
              "schema": {}
            }
          ]
        }
      ],
      "next": [
        {
          "path": "/a-ydych-chi-eisoes-wedi-gwario'r-cyllid-cyfatebol-rydych-wedi-sicrhau"
        }
      ],
      "section": "bgUGuD"
    },
    {
      "path": "/os-ydych-chi-wedi-iddo-nod-sicrhau-cyllid-cyfatebol-pellach",
      "title": "Os ydych chi wedi nodi i sicrhau cyllid cyfatebol pellach",
      "components": [
        {
          "name": "DmgsiG",
          "options": {},
          "type": "YesNoField",
          "title": "A ydych chi wedi nodi, ond heb ei sicrhau eto, unrhyw gyllid cyfatebol ychwanegol?"
        }
      ],
      "next": [
        {
          "path": "/cyllid-cyfatebol-refeni",
          "condition": "nPKnjf"
        },
        {
          "path": "/cyllid-cyfatebol-dihysbys",
          "condition": "DrELrt"
        }
      ],
      "section": "bgUGuD"
    },
    {
      "path": "/cyllid-cyfatebol-dihysbys",
      "title": "Cyllid cyfatebol dihysbys",
      "controller": "RepeatingFieldPageController",
      "options": {
        "summaryDisplayMode": {
          "samePage": true,
          "separatePage": false,
          "hideRowTitles": false
        },
        "customText": {
          "samePageTitle": "Eich cyllid cyfatebol dihysbys"
        }
      },
      "components": [
        {
          "name": "fixtAm",
          "options": {},
          "type": "Para",
          "content": "<label class=\"govuk-heading-s\">Cyllid cyfatebol dihysbys</label>\n\n<p class=\"govuk-hint\">Dywedwch wrthym pa ffynonellau cyllid rydych yn bwriadu eu sicrhau fel cyllid cyfatebol.</p>\n<p class=\"govuk-hint\">Gallwch ddefnyddio eich cynllun busnes i:</p>\n<ul class=\"govuk-list govuk-list--bullet govuk-caption-m govuk-!-padding-top-1\">\n<li>dweud wrthym pa mor hir y bydd yn debygol o gymryd amser i sicrhau unrhyw gyllid cyfatebol sydd heb ei dalu</li>\n<li>darparu unrhyw wybodaeth sy'n cefnogi eich atebion</li>\n</ul>"
        },
        {
          "name": "vEOdBS",
          "options": {
            "prefix": "£",
            "columnTitles": ["Ffynnonell", "Swm", "Gweithred"],
            "required": true
          },
          "type": "MultiInputField",
          "title": "Cyllid cyfatebol dihysbys",
          "hint": "Y MultiInputField sydd ei angen",
          "schema": {},
          "children": [
            {
              "name": "iMJdfs",
              "options": {},
              "type": "TextField",
              "title": "Ffynnonell o gyllid cyfatebol dihysbys"
            },
            {
              "name": "THOdae",
              "options": {
                "prefix": "£",
                "classes": "govuk-!-width-one-half"
              },
              "type": "NumberField",
              "title": "Swm",
              "hint": "",
              "schema": {}
            }
          ]
        }
      ],
      "next": [
        {
          "path": "/cyllid-cyfatebol-refeni"
        }
      ],
      "section": "bgUGuD"
    },
    {
      "path": "/cyllid-cyflogaeth",
      "title": "Cyllid cyflogaeth",
      "components": [
        {
          "name": "matkNH",
          "options": {},
          "type": "YesNoField",
          "title": "Ydych chi'n gwneud cais am gyllid cyflogaeth o Gronfa Perchnogaeth Gymunedol? (dewisol)",
          "hint": "Mae costau cyflogaeth yn mynd tuag at redeg yr ased ar ôl i chi gymryd perchnogaeth ohono. Gall hyn gynnwys costau cyffredinol, gan gynnwys am:\n\n<ul class=\"govuk-list govuk-list--bullet govuk-caption-m govuk-!-padding-top-2\">\n<li>cyfleusterau</li>\n<li>staffio</li>\n</ul>\n<p>Cofiwch, gallwch wneud cais am hyd at bump mil o bunnoedd (£5,000) o'ch costau cyflogaeth (dim mwy na 20% o'ch cyllid cyfalaf).</p>\n<p>Gallwch ddefnyddio eich cynllun busnes i ddarparu unrhyw wybodaeth sy'n cefnogi eich atebion</p>",
          "values": {
            "type": "listRef"
          }
        }
      ],
      "next": [
        {
          "path": "/costau-cyflogaeth-dewisol",
          "condition": "iegbPT"
        },
        {
          "path": "/crynhoi",
          "condition": "zVdAqG"
        }
      ],
      "section": "bgUGuD"
    },
    {
      "path": "/costau-cyflogaeth-dewisol",
      "title": "Costau cyflogaeth (dewisol)",
      "controller": "RepeatingFieldPageController",
      "options": {
        "summaryDisplayMode": {
          "samePage": true,
          "separatePage": false,
          "hideRowTitles": false
        },
        "customText": {
          "samePageTitle": "Eich costau cyflogaeth"
        }
      },
      "components": [
        {
          "name": "ngpQfE",
          "options": {},
          "type": "Details",
          "title": "Help gyda'r achos rheoli",
          "content": "Rydym yn ceisio deall:\n<div>\n<br>\n<ul class=\"govuk-list govuk-list--bullet\">\n<li>faint o gyllid rydych yn gwneud cais amdano o'r gronfa hon</li>\n<li>eich costau gweithredol llawn</li>\n<li>unrhyw gyllid rydych eisoes wedi'i dderbyn ar gyfer eich prosiect hyd yma</li>\n<li>unrhyw gyllid rydych yn bwriadu ei sicrhau ar gyfer eich prosiect</li>\n<li>unrhyw gyllid rydych eisoes wedi'i dderbyn tuag at gostau cyfalaf</li>\n</ul>\n<p>Gwnawn ofyn i chi uwchlwytho cynllun busnes i gefnogi'r atebion a roddwch inni yn yr adran hon.\n\nGall y gronfa hon gynnig hyd at 50% o'ch costau cyfalaf i adnewyddu a thrwsio'r ased.</p>\n</div>"
        },
        {
          "name": "FIXTaM",
          "options": {},
          "type": "Para",
          "content": "<label class=\"govuk-heading-s\">Costau cyflogaeth (dewisol)</label>\n\n<p class=\"govuk-hint\">Dywedwch wrthym am y costau cyflogaeth cyfansawdd o'ch prosiect.</p>\n<p class=\"govuk-hint\">Dyma'r costau rhedeg y prosiect. Gall hyn gynnwys costau cyffredinol, gan gynnwys am:</p>\n<ul class=\"govuk-list govuk-list--bullet govuk-caption-m govuk-!-padding-top-1\">\n<li>cyfleusterau</li>\n<li>staffio</li>\n</ul></p>\n<p class=\"govuk-hint\">Cofiwch, gallwch wneud cais am hyd at £50,000 o'ch costau cyflogaeth (dim mwy na 20% o'ch cyllid cyfalaf).\n\nGallwch ddefnyddio eich cynllun busnes i:</p>\n<ul class=\"govuk-list govuk-list--bullet govuk-caption-m govuk-!-padding-top-1\">\n<li>dweud wrthym pam rydych angen cyllid cyflogaeth</li>\n<li>darparu unrhyw wybodaeth sy'n cefnogi eich atebion</li>\n</ul>"
        },
        {
          "name": "VeoDbs",
          "options": {
            "prefix": "£",
            "columnTitles": ["Disgrifiad", "Swm", "Gweithred"],
            "required": true
          },
          "type": "MultiInputField",
          "title": "Costau cyflogaeth (dewisol)",
          "hint": "Y MultiInputField sydd ei angen",
          "schema": {},
          "children": [
            {
              "name": "ImjDFS",
              "options": {},
              "type": "TextField",
              "title": "Disgrifiad y gost"
            },
            {
              "name": "thoDAE",
              "options": {
                "prefix": "£",
                "classes": "govuk-!-width-one-half"
              },
              "type": "NumberField",
              "title": "Swm",
              "hint": "",
              "schema": {}
            }
          ]
        }
      ],
      "next": [
        {
          "path": "/crynhoi"
        }
      ],
      "section": "bgUGuD"
    },
    {
      "path": "/have-you-already-spent-the-match-funding-you-have-secured",
      "title": "Have you already spent the match funding you have secured?",
      "components": [
        {
          "name": "HgpNUe",
          "options": {
            "hideTitle": true
          },
          "type": "YesNoField",
          "hint": "Note that any funding that you have already spent will not be eligible as match funding",
          "title": "Have you already spent the match funding you have secured?"
        }
      ],
      "next": [
        {
          "path": "/if-youve-identified-further-match-funding"
        }
      ],
      "section": "bgUGuD"
    }
  ],
  "lists": [],
  "sections": [
    {
      "name": "bgUGuD",
      "title": "Funding required"
    }
  ],
  "conditions": [
    {
      "displayName": "Have you secured any match funding yet-yes",
      "name": "QyNLbn",
      "value": {
        "name": "Have you secured any match funding yet-yes",
        "conditions": [
          {
            "field": {
              "name": "DOvZvB",
              "type": "YesNoField",
              "display": "Have you secured any match funding yet?"
            },
            "operator": "is",
            "value": {
              "type": "Value",
              "value": "true",
              "display": "true"
            }
          }
        ]
      }
    },
    {
      "displayName": "Have you secured any match funding yet-no",
      "name": "nzrkpu",
      "value": {
        "name": "Have you secured any match funding yet-no",
        "conditions": [
          {
            "field": {
              "name": "DOvZvB",
              "type": "YesNoField",
              "display": "Have you secured any match funding yet?"
            },
            "operator": "is",
            "value": {
              "type": "Value",
              "value": "false",
              "display": "false"
            }
          }
        ]
      }
    },
    {
      "displayName": "Do you have any match funding identified but not yet secured-yes",
      "name": "DrELrt",
      "value": {
        "name": "Do you have any match funding identified but not yet secured-yes",
        "conditions": [
          {
            "field": {
              "name": "DmgsiG",
              "type": "YesNoField",
              "display": "Do you have any match funding identified but not yet secured?"
            },
            "operator": "is",
            "value": {
              "type": "Value",
              "value": "true",
              "display": "true"
            }
          }
        ]
      }
    },
    {
      "displayName": "Do you have any match funding identified but not yet secured-no",
      "name": "nPKnjf",
      "value": {
        "name": "Do you have any match funding identified but not yet secured-no",
        "conditions": [
          {
            "field": {
              "name": "DmgsiG",
              "type": "YesNoField",
              "display": "Do you have any match funding identified but not yet secured?"
            },
            "operator": "is",
            "value": {
              "type": "Value",
              "value": "false",
              "display": "false"
            }
          }
        ]
      }
    },
    {
      "displayName": "Are you applying for revenue funding from the Community Ownership Fund-yes",
      "name": "iegbPT",
      "value": {
        "name": "Are you applying for revenue funding from the Community Ownership Fund-yes",
        "conditions": [
          {
            "field": {
              "name": "matkNH",
              "type": "YesNoField",
              "display": "Are you applying for revenue funding from the Community Ownership Fund? (optional)"
            },
            "operator": "is",
            "value": {
              "type": "Value",
              "value": "true",
              "display": "true"
            }
          }
        ]
      }
    },
    {
      "displayName": "Are you applying for revenue funding from the Community Ownership Fund-no",
      "name": "zVdAqG",
      "value": {
        "name": "Are you applying for revenue funding from the Community Ownership Fund-no",
        "conditions": [
          {
            "field": {
              "name": "matkNH",
              "type": "YesNoField",
              "display": "Are you applying for revenue funding from the Community Ownership Fund? (optional)"
            },
            "operator": "is",
            "value": {
              "type": "Value",
              "value": "false",
              "display": "false"
            }
          }
        ]
      }
    }
  ],
  "fees": [],
  "outputs": [
    {
      "name": "update-form",
      "title": "Diweddaru'r ffurflen yn y cais",
      "type": "savePerPage",
      "outputConfiguration": {
        "savePerPageUrl": "True"
      }
    }
  ],
  "version": 2,
  "skipSummary": false,
  "name": "Gwneud cais am gyllid i achub ased yn eich cymuned",
  "feedback": {
    "feedbackForm": false,
    "url": ""
  },
  "phaseBanner": {
    "phase": "beta"
  }
}
