{
  "server": {
    "host": "localhost",
    "port": 3009
  },
  "logging": {
    "ops": {
      "interval": 1000
    },
    "reporters": {
      "console": [
        {
          "module": "good-squeeze",
          "name": "Squeeze",
          "args": [
            {
              "log": "*",
              "error": "*",
              "response": "*",
              "request": "*"
            }
          ]
        },
        {
          "module": "good-console"
        },
        "stdout"
      ]
    }
  },
  "views": {
    "cache": false
  },
  "ordnanceSurveyKey": "enter-ordnance-survey-postcode-key-here"
}
