{
  "startPage": "/start-ukhsa-webform",
  "pages": [
    {
      "path": "/start-ukhsa-webform",
      "title": "Welcome to the form",
      "components": [
        {
          "name": "UccVyu",
          "options": {},
          "type": "Para",
          "content": "Lorem ipsum dolor sit amet consectetur, adipisicing elit. Eos natus consequuntur ratione dolorum ad, saepe voluptatibus sed necessitatibus tempore distinctio voluptates laborum hic temporibus voluptatem, exercitationem pariatur nam, asperiores odit et! Exercitationem, natus recusandae quod quas ipsum cum, perferendis ex provident adipisci ad doloremque dicta aperiam molestiae aut ipsa. Voluptate."
        }
      ],
      "next": [{ "path": "/interaction" }],
      "controller": "./pages/start.js"
    },
    {
      "title": "Please tell us the name of the last person you interacted with at the Gym/swimming pool",
      "path": "/interaction",
      "components": [
        {
          "name": "agLBwI",
          "options": {},
          "type": "Para",
          "content": "These could be people you spend 15 minutes or more with, at a distance of less than two metres",
          "schema": {}
        },
        {
          "type": "TextField",
          "title": "First name",
          "name": "FirstName",
          "nameHasError": false,
          "schema": { "min": 1, "max": 25 },
          "options": {}
        },
        {
          "name": "LastName",
          "options": {},
          "type": "TextField",
          "title": "Last name",
          "nameHasError": false,
          "schema": { "min": 1, "max": 25 }
        }
      ],
      "next": [{ "path": "/activities" }],
      "section": "Close_contact_detail"
    },
    {
      "path": "/activities",
      "title": "When were you at the Gym/swimming pool?",
      "components": [
        {
          "name": "BPXMnm",
          "options": {},
          "type": "Para",
          "content": "For example, 27 3 2007",
          "schema": {}
        },
        {
          "name": "ActivityDate",
          "options": { "hideTitle": true },
          "type": "DatePartsField",
          "title": "Date",
          "nameHasError": false,
          "schema": {}
        }
      ],
      "next": [{ "path": "/activitydetail" }],
      "section": "Activities_outside_your_home"
    },
    {
      "path": "/activitydetail",
      "title": "How many people were at the Gym/ swimming pool?",
      "components": [
        {
          "name": "GinBFX",
          "options": {},
          "type": "Para",
          "content": "Please select a range of people you had close contact with",
          "schema": {}
        },
        {
          "name": "Number_of_People",
          "options": { "hideTitle": true },
          "type": "RadiosField",
          "title": "Number of People",
          "nameHasError": false,
          "list": "oSyvBD",
          "schema": {}
        }
      ],
      "next": [{ "path": "/activities_list" }],
      "section": "Activities"
    },
    {
      "path": "/activities_list",
      "title": "Please select all the activities you have done in the last 10 days",
      "components": [
        {
          "name": "ZADApp",
          "options": {},
          "type": "Para",
          "content": "It is important to inform us what activities you have been doing between Monday (1 June) to Friday (5 June) and provide details.",
          "schema": {}
        },
        {
          "name": "KykFmw",
          "options": {},
          "type": "Para",
          "content": "This will help us understand where you may have exposed to [DISEASE NAME]",
          "schema": {}
        },
        {
          "name": "Activity_Location",
          "options": { "hideTitle": true },
          "type": "CheckboxesField",
          "title": "Activity Location",
          "nameHasError": false,
          "list": "dBWWHg",
          "schema": {}
        }
      ],
      "next": [{ "path": "/summary" }],
      "section": "activities_number"
    },
    {
      "path": "/summary",
      "title": "Summary",
      "components": [],
      "next": [],
      "section": "Review",
      "controller": "./pages/summary.js"
    }
  ],
  "lists": [
    {
      "title": "Number of people",
      "name": "oSyvBD",
      "type": "string",
      "items": [
        { "text": "1", "value": 1 },
        { "text": "2-5", "value": "2-5" },
        { "text": "5-9", "value": "5-9" },
        { "text": "10+", "value": "10+" },
        { "text": "None", "value": "None" }
      ]
    },
    {
      "title": "Activity Location",
      "name": "dBWWHg",
      "type": "string",
      "items": [
        { "text": "Festival", "value": "Festival" },
        { "text": "Organised event", "value": "Organised event" },
        { "text": "Sports events", "value": "Sports event" },
        { "text": "Shopping", "value": "Shopping" },
        { "text": "Sauna", "value": "Sauna" },
        {
          "text": "Travel and communicating",
          "value": "Travel and communicating"
        },
        { "text": "Bar", "value": "Bar" },
        { "text": "Gym/ swimming pool", "value": "Gym/ swimming pool" }
      ]
    }
  ],
  "sections": [
    {
      "name": "Close_contact_detail",
      "title": "Close contact's personal details"
    },
    {
      "name": "Activities_outside_your_home",
      "title": "Activities outside your home"
    },
    { "name": "Activities", "title": "Activities outside your home" },
    { "name": "activities_number", "title": "Activities outside your home" },
    { "name": "Review", "title": "Review your responses" }
  ],
  "conditions": [],
  "fees": [],
  "outputs": [
    {
      "name": "wbOnTy",
      "title": "submit-data-webhook",
      "type": "webhook",
      "outputConfiguration": {
        "url": "https://api.devwebforms.test-and-trace.nhs.uk/webforms-submit-form-data"
      }
    }
  ],
  "version": 2,
  "skipSummary": false,
  "declaration": "",
  "name": "updated-ukhsa-webform",
  "feedback": { "feedbackForm": false, "url": "/updated-feedback-form" },
  "phaseBanner": { "phase": "beta" }
}
